{"meta":{"nextPageToken":"","previousPageToken":"v1:3","numFound":"474","properties":[]},"items":[{"id":"m17145291169","sellerId":"454375176","buyerId":"","status":"ITEM_STATUS_SOLD_OUT","name":"ドラゴンクエストVII リメイク Nintendo Switch","price":"3980","created":"1778566459","updated":"1778842802","thumbnails":["https://static.mercdn.net/thumb/item/webp/m17145291169_1.jpg?1778566459"],"itemType":"ITEM_TYPE_MERCARI","itemConditionId":"3","shippingPayerId":"2","itemSizes":[],"itemBrand":null,"itemPromotions":[],"shopName":"","itemSize":null,"shippingMethodId":"14","categoryId":"7015","isNoPrice":false,"title":"","isLiked":false,"photos":[{"uri":"https://static.mercdn.net/item/detail/webp/photos/m17145291169_1.jpg?1778566459"}],"auction":null,"shop":null,"attributes":[]},{"id":"m84769499464","sellerId":"388971789","buyerId":"","status":"ITEM_STATUS_SOLD_OUT","name":"ドラゴンクエストVII リメイク Nintendo Switch","price":"4700","created":"1776768889","updated":"1777215452","thumbnails":["https://static.mercdn.net/thumb/item/webp/m84769499464_1.jpg?1776768889"],"itemType":"ITEM_TYPE_MERCARI","itemConditionId":"3","shippingPayerId":"2","itemSizes":[],"itemBrand":null,"itemPromotions":[],"shopName":"","itemSize":null,"shippingMethodId":"17","categoryId":"702","isNoPrice":false,"title":"","isLiked":false,"photos":[{"uri":"https://static.mercdn.net/item/detail/webp/photos/m84769499464_1.jpg?1776768889"}],"auction":null,"shop":null,"attributes":[]},{"id":"m62545316913","sellerId":"368434974","buyerId":"","status":"ITEM_STATUS_SOLD_OUT","name":"ドラゴンクエスト7 リメイク版","price":"4350","created":"1777344517","updated":"1777619903","thumbnails":["https://static.mercdn.net/thumb/item/webp/m62545316913_1.jpg?1777344517"],"itemType":"ITEM_TYPE_MERCARI","itemConditionId":"3","shippingPayerId":"2","itemSizes":[],"itemBrand":null,"itemPromotions":[],"shopName":"","itemSize":null,"shippingMethodId":"17","categoryId":"7015","isNoPrice":false,"title":"","isLiked":false,"photos":[{"uri":"https://static.mercdn.net/item/detail/webp/photos/m62545316913_1.jpg?1777344517"}],"auction":null,"shop":null,"attributes":[]},{"id":"m66367601644","sellerId":"117117367","buyerId":"","status":"ITEM_STATUS_SOLD_OUT","name":"ドラゴンクエストVII リメイク Nintendo Switch2 特典付","price":"4100","created":"1776302577","updated":"1779602515","thumbnails":["https://static.mercdn.net/thumb/item/webp/m66367601644_1.jpg?1776302577"],"itemType":"ITEM_TYPE_MERCARI","itemConditionId":"3","shippingPayerId":"2","itemSizes":[],"itemBrand":null,"itemPromotions":[],"shopName":"","itemSize":null,"shippingMethodId":"17","categoryId":"7015","isNoPrice":false,"title":"","isLiked":false,"photos":[{"uri":"https://static.mercdn.net/item/detail/webp/photos/m66367601644_1.jpg?1776302577"}],"auction":null,"shop":null,"attributes":[]},{"id":"m96859258357","sellerId":"801424422","buyerId":"","status":"ITEM_STATUS_SOLD_OUT","name":"ドラゴンクエスト7リイマジンド　Switch2 リメイク","price":"7300","created":"1770623015","updated":"1770911478","thumbnails":["https://static.mercdn.net/thumb/item/webp/m96859258357_1.jpg?1770623015"],"itemType":"ITEM_TYPE_MERCARI","itemConditionId":"3","shippingPayerId":"2","itemSizes":[],"itemBrand":null,"itemPromotions":[],"shopName":"","itemSize":null,"shippingMethodId":"14","categoryId":"7015","isNoPrice":false,"title":"","isLiked":false,"photos":[{"uri":"https://static.mercdn.net/item/detail/webp/photos/m96859258357_1.jpg?1770623015"}],"auction":null,"shop":null,"attributes":[]},{"id":"m11039081491","sellerId":"892564464","buyerId":"","status":"ITEM_STATUS_TRADING","name":"ドラゴンクエスト Ⅶ Reimagined（Switch2版）","price":"4250","created":"1782050151","updated":"1782057963","thumbnails":["https://static.mercdn.net/thumb/item/webp/m11039081491_1.jpg?1782050151"],"itemType":"ITEM_TYPE_MERCARI","itemConditionId":"2","shippingPayerId":"2","itemSizes":[],"itemBrand":null,"itemPromotions":[],"shopName":"","itemSize":null,"shippingMethodId":"17","categoryId":"7015","isNoPrice":false,"title":"","isLiked":false,"photos":[{"uri":"https://static.mercdn.net/item/detail/webp/photos/m11039081491_1.jpg?1782050151"}],"auction":null,"shop":null,"attributes":[]},{"id":"m14509263254","sellerId":"137266620","buyerId":"","status":"ITEM_STATUS_SOLD_OUT","name":"ドラゴンクエストVII リメイク Nintendo Switch2","price":"5000","created":"1774523725","updated":"1774944659","thumbnails":["https://static.mercdn.net/thumb/item/webp/m14509263254_1.jpg?1774523725"],"itemType":"ITEM_TYPE_MERCARI","itemConditionId":"3","shippingPayerId":"2","itemSizes":[],"itemBrand":null,"itemPromotions":[],"shopName":"","itemSize":null,"shippingMethodId":"14","categoryId":"7015","isNoPrice":false,"title":"","isLiked":false,"photos":[{"uri":"https://static.mercdn.net/item/detail/webp/photos/m14509263254_1.jpg?1774523725"}],"auction":null,"shop":null,"attributes":[]},{"id":"m14492101856","sellerId":"623091829","buyerId":"","status":"ITEM_STATUS_SOLD_OUT","name":"DRAGON QUEST VII リメイク　switch2版","price":"7800","created":"1770294436","updated":"1770520718","thumbnails":["https://static.mercdn.net/thumb/item/webp/m14492101856_1.jpg?1770294436"],"itemType":"ITEM_TYPE_MERCARI","itemConditionId":"1","shippingPayerId":"2","itemSizes":[],"itemBrand":null,"itemPromotions":[],"shopName":"","itemSize":null,"shippingMethodId":"14","categoryId":"7015","isNoPrice":false,"title":"","isLiked":false,"photos":[{"uri":"https://static.mercdn.net/item/detail/webp/photos/m14492101856_1.jpg?1770294436"}],"auction":null,"shop":null,"attributes":[]},{"id":"m42780567708","sellerId":"836513644","buyerId":"","status":"ITEM_STATUS_SOLD_OUT","name":"ドラゴンクエストVII リメイク Nintendo Switch2","price":"5000","created":"1774663402","updated":"1775061341","thumbnails":["https://static.mercdn.net/thumb/item/webp/m42780567708_1.jpg?1774663402"],"itemType":"ITEM_TYPE_MERCARI","itemConditionId":"3","shippingPayerId":"2","itemSizes":[],"itemBrand":null,"itemPromotions":[],"shopName":"","itemSize":null,"shippingMethodId":"17","categoryId":"7015","isNoPrice":false,"title":"","isLiked":false,"photos":[{"uri":"https://static.mercdn.net/item/detail/webp/photos/m42780567708_1.jpg?1774663402"}],"auction":null,"shop":null,"attributes":[]},{"id":"m54683971579","sellerId":"735467514","buyerId":"","status":"ITEM_STATUS_SOLD_OUT","name":"ドラゴンクエスト7リメイク Switch2 早期特典コード未使用","price":"6100","created":"1771820580","updated":"1771931915","thumbnails":["https://static.mercdn.net/thumb/item/webp/m54683971579_1.jpg?1771820580"],"itemType":"ITEM_TYPE_MERCARI","itemConditionId":"3","shippingPayerId":"2","itemSizes":[],"itemBrand":null,"itemPromotions":[],"shopName":"","itemSize":null,"shippingMethodId":"14","categoryId":"7015","isNoPrice":false,"title":"","isLiked":false,"photos":[{"uri":"https://static.mercdn.net/item/detail/webp/photos/m54683971579_1.jpg?1771820580"}],"auction":null,"shop":null,"attributes":[]},{"id":"m76303584885","sellerId":"527948640","buyerId":"","status":"ITEM_STATUS_SOLD_OUT","name":"ドラゴンクエストVII リメイク Nintendo Switch","price":"5200","created":"1775537846","updated":"1775778109","thumbnails":["https://static.mercdn.net/thumb/item/webp/m76303584885_1.jpg?1775537846"],"itemType":"ITEM_TYPE_MERCARI","itemConditionId":"3","shippingPayerId":"2","itemSizes":[],"itemBrand":null,"itemPromotions":[],"shopName":"","itemSize":null,"shippingMethodId":"14","categoryId":"702","isNoPrice":false,"title":"","isLiked":false,"photos":[{"uri":"https://static.mercdn.net/item/detail/webp/photos/m76303584885_1.jpg?1775537846"}],"auction":null,"shop":null,"attributes":[]},{"id":"m64269785388","sellerId":"840370153","buyerId":"","status":"ITEM_STATUS_SOLD_OUT","name":"Switch2　ドラゴンクエスト7 Reimagined リメイク","price":"5800","created":"1772555056","updated":"1772706940","thumbnails":["https://static.mercdn.net/thumb/item/webp/m64269785388_1.jpg?1772555056"],"itemType":"ITEM_TYPE_MERCARI","itemConditionId":"3","shippingPayerId":"2","itemSizes":[],"itemBrand":null,"itemPromotions":[],"shopName":"","itemSize":null,"shippingMethodId":"14","categoryId":"7015","isNoPrice":false,"title":"","isLiked":false,"photos":[{"uri":"https://static.mercdn.net/item/detail/webp/photos/m64269785388_1.jpg?1772555056"}],"auction":null,"shop":null,"attributes":[]},{"id":"m91929407363","sellerId":"230694209","buyerId":"","status":"ITEM_STATUS_SOLD_OUT","name":"【switch2】ドラゴンクエスト7 リメイク コード未使用","price":"6500","created":"1771142642","updated":"1771838076","thumbnails":["https://static.mercdn.net/thumb/item/webp/m91929407363_1.jpg?1771142642"],"itemType":"ITEM_TYPE_MERCARI","itemConditionId":"2","shippingPayerId":"2","itemSizes":[],"itemBrand":null,"itemPromotions":[],"shopName":"","itemSize":null,"shippingMethodId":"14","categoryId":"7015","isNoPrice":false,"title":"","isLiked":false,"photos":[{"uri":"https://static.mercdn.net/item/detail/webp/photos/m91929407363_1.jpg?1771142642"}],"auction":null,"shop":null,"attributes":[]},{"id":"m87218409192","sellerId":"174811527","buyerId":"","status":"ITEM_STATUS_SOLD_OUT","name":"ドラゴンクエスト7 リメイク","price":"5000","created":"1775345642","updated":"1775779341","thumbnails":["https://static.mercdn.net/thumb/item/webp/m87218409192_1.jpg?1775345642"],"itemType":"ITEM_TYPE_MERCARI","itemConditionId":"2","shippingPayerId":"2","itemSizes":[],"itemBrand":null,"itemPromotions":[],"shopName":"","itemSize":null,"shippingMethodId":"14","categoryId":"7015","isNoPrice":false,"title":"","isLiked":false,"photos":[{"uri":"https://static.mercdn.net/item/detail/webp/photos/m87218409192_1.jpg?1775345642"}],"auction":null,"shop":null,"attributes":[]},{"id":"m33400555629","sellerId":"843283482","buyerId":"","status":"ITEM_STATUS_SOLD_OUT","name":"ドラゴンクエストVII リメイク Nintendo Switch2","price":"4500","created":"1778819993","updated":"1780271817","thumbnails":["https://static.mercdn.net/thumb/item/webp/m33400555629_1.jpg?1778819993"],"itemType":"ITEM_TYPE_MERCARI","itemConditionId":"3","shippingPayerId":"2","itemSizes":[],"itemBrand":null,"itemPromotions":[],"shopName":"","itemSize":null,"shippingMethodId":"17","categoryId":"7015","isNoPrice":false,"title":"","isLiked":false,"photos":[{"uri":"https://static.mercdn.net/item/detail/webp/photos/m33400555629_1.jpg?1778819993"}],"auction":null,"shop":null,"attributes":[]},{"id":"m64577540240","sellerId":"918800274","buyerId":"","status":"ITEM_STATUS_SOLD_OUT","name":"あ*ん様 ドラゴンクエストVII リメイク Nintendo Switch","price":"4100","created":"1776766108","updated":"1777895879","thumbnails":["https://static.mercdn.net/thumb/item/webp/m64577540240_1.jpg?1776766108"],"itemType":"ITEM_TYPE_MERCARI","itemConditionId":"2","shippingPayerId":"2","itemSizes":[],"itemBrand":null,"itemPromotions":[],"shopName":"","itemSize":null,"shippingMethodId":"14","categoryId":"7015","isNoPrice":false,"title":"","isLiked":false,"photos":[{"uri":"https://static.mercdn.net/item/detail/webp/photos/m64577540240_1.jpg?1776766108"}],"auction":null,"shop":null,"attributes":[]},{"id":"m86567269241","sellerId":"607036317","buyerId":"","status":"ITEM_STATUS_SOLD_OUT","name":"ドラゴンクエストVII Reimagined","price":"4200","created":"1777103930","updated":"1777291602","thumbnails":["https://static.mercdn.net/thumb/item/webp/m86567269241_1.jpg?1777103930"],"itemType":"ITEM_TYPE_MERCARI","itemConditionId":"3","shippingPayerId":"2","itemSizes":[],"itemBrand":null,"itemPromotions":[],"shopName":"","itemSize":null,"shippingMethodId":"17","categoryId":"7015","isNoPrice":false,"title":"","isLiked":false,"photos":[{"uri":"https://static.mercdn.net/item/detail/webp/photos/m86567269241_1.jpg?1777103930"}],"auction":null,"shop":null,"attributes":[]},{"id":"m77959566234","sellerId":"738490218","buyerId":"","status":"ITEM_STATUS_SOLD_OUT","name":"ドラゴンクエスト7 リメイク　VII Reimagined Switch2専用","price":"6400","created":"1771323274","updated":"1771598096","thumbnails":["https://static.mercdn.net/thumb/item/webp/m77959566234_1.jpg?1771323274"],"itemType":"ITEM_TYPE_MERCARI","itemConditionId":"3","shippingPayerId":"2","itemSizes":[],"itemBrand":null,"itemPromotions":[],"shopName":"","itemSize":null,"shippingMethodId":"14","categoryId":"7015","isNoPrice":false,"title":"","isLiked":false,"photos":[{"uri":"https://static.mercdn.net/item/detail/webp/photos/m77959566234_1.jpg?1771323274"}],"auction":null,"shop":null,"attributes":[]},{"id":"m87041532590","sellerId":"680896320","buyerId":"","status":"ITEM_STATUS_SOLD_OUT","name":"ドラゴンクエスト7 リメイク　VII Reimagined Switch2専用","price":"6400","created":"1771326326","updated":"1771592073","thumbnails":["https://static.mercdn.net/thumb/item/webp/m87041532590_1.jpg?1771326326"],"itemType":"ITEM_TYPE_MERCARI","itemConditionId":"2","shippingPayerId":"2","itemSizes":[],"itemBrand":null,"itemPromotions":[],"shopName":"","itemSize":null,"shippingMethodId":"17","categoryId":"7015","isNoPrice":false,"title":"","isLiked":false,"photos":[{"uri":"https://static.mercdn.net/item/detail/webp/photos/m87041532590_1.jpg?1771326326"}],"auction":null,"shop":null,"attributes":[]},{"id":"m13757894998","sellerId":"451211127","buyerId":"","status":"ITEM_STATUS_SOLD_OUT","name":"ドラゴンクエストVII リメイク Nintendo Switch2","price":"4699","created":"1775351736","updated":"1775599091","thumbnails":["https://static.mercdn.net/thumb/item/webp/m13757894998_1.jpg?1775351736"],"itemType":"ITEM_TYPE_MERCARI","itemConditionId":"3","shippingPayerId":"2","itemSizes":[],"itemBrand":null,"itemPromotions":[],"shopName":"","itemSize":null,"shippingMethodId":"14","categoryId":"7015","isNoPrice":false,"title":"","isLiked":false,"photos":[{"uri":"https://static.mercdn.net/item/detail/webp/photos/m13757894998_1.jpg?1775351736"}],"auction":null,"shop":null,"attributes":[]},{"id":"m92108144189","sellerId":"501188780","buyerId":"","status":"ITEM_STATUS_SOLD_OUT","name":"【switch2】ドラゴンクエスト7 リメイク コード未使用","price":"6888","created":"1771135352","updated":"1771414876","thumbnails":["https://static.mercdn.net/thumb/item/webp/m92108144189_1.jpg?1771135352"],"itemType":"ITEM_TYPE_MERCARI","itemConditionId":"3","shippingPayerId":"2","itemSizes":[],"itemBrand":null,"itemPromotions":[],"shopName":"","itemSize":null,"shippingMethodId":"14","categoryId":"7015","isNoPrice":false,"title":"","isLiked":false,"photos":[{"uri":"https://static.mercdn.net/item/detail/webp/photos/m92108144189_1.jpg?1771135352"}],"auction":null,"shop":null,"attributes":[]},{"id":"m42195592338","sellerId":"402748245","buyerId":"","status":"ITEM_STATUS_SOLD_OUT","name":"ドラゴンクエスト7 リメイク","price":"5150","created":"1773659533","updated":"1774456517","thumbnails":["https://static.mercdn.net/thumb/item/webp/m42195592338_1.jpg?1773659533"],"itemType":"ITEM_TYPE_MERCARI","itemConditionId":"3","shippingPayerId":"2","itemSizes":[],"itemBrand":null,"itemPromotions":[],"shopName":"","itemSize":null,"shippingMethodId":"14","categoryId":"7015","isNoPrice":false,"title":"","isLiked":false,"photos":[{"uri":"https://static.mercdn.net/item/detail/webp/photos/m42195592338_1.jpg?1773659533"}],"auction":null,"shop":null,"attributes":[]},{"id":"m12993993529","sellerId":"245870904","buyerId":"","status":"ITEM_STATUS_SOLD_OUT","name":"ドラゴンクエストVII リメイク switch2　コード未使用","price":"4500","created":"1777197565","updated":"1777563906","thumbnails":["https://static.mercdn.net/thumb/item/webp/m12993993529_1.jpg?1777197565"],"itemType":"ITEM_TYPE_MERCARI","itemConditionId":"3","shippingPayerId":"2","itemSizes":[],"itemBrand":null,"itemPromotions":[],"shopName":"","itemSize":null,"shippingMethodId":"14","categoryId":"7015","isNoPrice":false,"title":"","isLiked":false,"photos":[{"uri":"https://static.mercdn.net/item/detail/webp/photos/m12993993529_1.jpg?1777197565"}],"auction":null,"shop":null,"attributes":[]},{"id":"m53282178785","sellerId":"719075706","buyerId":"","status":"ITEM_STATUS_SOLD_OUT","name":"DRAGON QUEST VII Reimagined(初回特典あり)","price":"4200","created":"1777096745","updated":"1777602188","thumbnails":["https://static.mercdn.net/thumb/item/webp/m53282178785_1.jpg?1777096745"],"itemType":"ITEM_TYPE_MERCARI","itemConditionId":"4","shippingPayerId":"2","itemSizes":[],"itemBrand":null,"itemPromotions":[],"shopName":"","itemSize":null,"shippingMethodId":"14","categoryId":"7015","isNoPrice":false,"title":"","isLiked":false,"photos":[{"uri":"https://static.mercdn.net/item/detail/webp/photos/m53282178785_1.jpg?1777096745"}],"auction":null,"shop":null,"attributes":[]},{"id":"m36352754592","sellerId":"578092094","buyerId":"","status":"ITEM_STATUS_SOLD_OUT","name":"ドラゴンクエスト7リメイク Switch2","price":"4400","created":"1780911920","updated":"1781217491","thumbnails":["https://static.mercdn.net/thumb/item/webp/m36352754592_1.jpg?1780911920"],"itemType":"ITEM_TYPE_MERCARI","itemConditionId":"3","shippingPayerId":"2","itemSizes":[],"itemBrand":null,"itemPromotions":[],"shopName":"","itemSize":null,"shippingMethodId":"14","categoryId":"7015","isNoPrice":false,"title":"","isLiked":false,"photos":[{"uri":"https://static.mercdn.net/item/detail/webp/photos/m36352754592_1.jpg?1780911920"}],"auction":null,"shop":null,"attributes":[]},{"id":"m64536123611","sellerId":"561476907","buyerId":"","status":"ITEM_STATUS_TRADING","name":"Switch2 DRAGON QUEST VII Reimagined","price":"4400","created":"1781871523","updated":"1781928924","thumbnails":["https://static.mercdn.net/thumb/item/webp/m64536123611_1.jpg?1781871523"],"itemType":"ITEM_TYPE_MERCARI","itemConditionId":"4","shippingPayerId":"2","itemSizes":[],"itemBrand":null,"itemPromotions":[],"shopName":"","itemSize":null,"shippingMethodId":"17","categoryId":"7015","isNoPrice":false,"title":"","isLiked":false,"photos":[{"uri":"https://static.mercdn.net/item/detail/webp/photos/m64536123611_1.jpg?1781871523"}],"auction":null,"shop":null,"attributes":[]},{"id":"m92218881519","sellerId":"190927352","buyerId":"","status":"ITEM_STATUS_SOLD_OUT","name":"ドラゴンクエストVII リメイク Nintendo Switch2","price":"4200","created":"1777859860","updated":"1778080319","thumbnails":["https://static.mercdn.net/thumb/item/webp/m92218881519_1.jpg?1777859860"],"itemType":"ITEM_TYPE_MERCARI","itemConditionId":"3","shippingPayerId":"2","itemSizes":[],"itemBrand":null,"itemPromotions":[],"shopName":"","itemSize":null,"shippingMethodId":"14","categoryId":"7015","isNoPrice":false,"title":"","isLiked":false,"photos":[{"uri":"https://static.mercdn.net/item/detail/webp/photos/m92218881519_1.jpg?1777859860"}],"auction":null,"shop":null,"attributes":[]},{"id":"m43114748986","sellerId":"408916260","buyerId":"","status":"ITEM_STATUS_SOLD_OUT","name":"ドラゴンクエスト7リメイク","price":"4800","created":"1775717476","updated":"1776244005","thumbnails":["https://static.mercdn.net/thumb/item/webp/m43114748986_1.jpg?1775717476"],"itemType":"ITEM_TYPE_MERCARI","itemConditionId":"3","shippingPayerId":"2","itemSizes":[],"itemBrand":null,"itemPromotions":[],"shopName":"","itemSize":null,"shippingMethodId":"17","categoryId":"7015","isNoPrice":false,"title":"","isLiked":false,"photos":[{"uri":"https://static.mercdn.net/item/detail/webp/photos/m43114748986_1.jpg?1775717476"}],"auction":null,"shop":null,"attributes":[]},{"id":"m77621492957","sellerId":"954050649","buyerId":"","status":"ITEM_STATUS_SOLD_OUT","name":"ドラゴンクエスト7 リメイク版 リイマジンド","price":"7500","created":"1770573100","updated":"1770717548","thumbnails":["https://static.mercdn.net/thumb/item/webp/m77621492957_1.jpg?1770573100"],"itemType":"ITEM_TYPE_MERCARI","itemConditionId":"2","shippingPayerId":"2","itemSizes":[],"itemBrand":null,"itemPromotions":[],"shopName":"","itemSize":null,"shippingMethodId":"13","categoryId":"7015","isNoPrice":false,"title":"","isLiked":false,"photos":[{"uri":"https://static.mercdn.net/item/detail/webp/photos/m77621492957_1.jpg?1770573100"}],"auction":null,"shop":null,"attributes":[]},{"id":"m71299404426","sellerId":"743184472","buyerId":"","status":"ITEM_STATUS_SOLD_OUT","name":"ドラゴンクエストVII リメイク Nintendo Switch","price":"4690","created":"1777636078","updated":"1777968595","thumbnails":["https://static.mercdn.net/thumb/item/webp/m71299404426_1.jpg?1777636078"],"itemType":"ITEM_TYPE_MERCARI","itemConditionId":"3","shippingPayerId":"2","itemSizes":[],"itemBrand":null,"itemPromotions":[],"shopName":"","itemSize":null,"shippingMethodId":"17","categoryId":"702","isNoPrice":false,"title":"","isLiked":false,"photos":[{"uri":"https://static.mercdn.net/item/detail/webp/photos/m71299404426_1.jpg?1777636078"}],"auction":null,"shop":null,"attributes":[]},{"id":"m64946138084","sellerId":"439493889","buyerId":"","status":"ITEM_STATUS_SOLD_OUT","name":"ドラゴンクエスト7 リメイク","price":"6300","created":"1771641897","updated":"1771913440","thumbnails":["https://static.mercdn.net/thumb/item/webp/m64946138084_1.jpg?1771641897"],"itemType":"ITEM_TYPE_MERCARI","itemConditionId":"3","shippingPayerId":"2","itemSizes":[],"itemBrand":null,"itemPromotions":[],"shopName":"","itemSize":null,"shippingMethodId":"14","categoryId":"7015","isNoPrice":false,"title":"","isLiked":false,"photos":[{"uri":"https://static.mercdn.net/item/detail/webp/photos/m64946138084_1.jpg?1771641897"}],"auction":null,"shop":null,"attributes":[]},{"id":"m57409322782","sellerId":"639325853","buyerId":"","status":"ITEM_STATUS_SOLD_OUT","name":"【初回特典未使用】ドラゴンクエスト　7 VII リメイク スイッチ","price":"5400","created":"1775357688","updated":"1775619175","thumbnails":["https://static.mercdn.net/thumb/item/webp/m57409322782_1.jpg?1775357688"],"itemType":"ITEM_TYPE_MERCARI","itemConditionId":"3","shippingPayerId":"2","itemSizes":[],"itemBrand":null,"itemPromotions":[],"shopName":"","itemSize":null,"shippingMethodId":"17","categoryId":"702","isNoPrice":false,"title":"","isLiked":false,"photos":[{"uri":"https://static.mercdn.net/item/detail/webp/photos/m57409322782_1.jpg?1775357688"}],"auction":null,"shop":null,"attributes":[]},{"id":"m97550762834","sellerId":"735595291","buyerId":"","status":"ITEM_STATUS_SOLD_OUT","name":"ドラゴンクエスト3 スイッチ版　リメイク","price":"2500","created":"1780755146","updated":"1781346347","thumbnails":["https://static.mercdn.net/thumb/item/webp/m97550762834_1.jpg?1780755146"],"itemType":"ITEM_TYPE_MERCARI","itemConditionId":"3","shippingPayerId":"2","itemSizes":[],"itemBrand":null,"itemPromotions":[],"shopName":"","itemSize":null,"shippingMethodId":"14","categoryId":"702","isNoPrice":false,"title":"","isLiked":false,"photos":[{"uri":"https://static.mercdn.net/item/detail/webp/photos/m97550762834_1.jpg?1780755146"}],"auction":null,"shop":null,"attributes":[]},{"id":"m29051587548","sellerId":"340192291","buyerId":"","status":"ITEM_STATUS_SOLD_OUT","name":"ドラゴンクエストVII リメイク Nintendo Switch2","price":"4890","created":"1775870311","updated":"1775986213","thumbnails":["https://static.mercdn.net/thumb/item/webp/m29051587548_1.jpg?1775870311"],"itemType":"ITEM_TYPE_MERCARI","itemConditionId":"3","shippingPayerId":"2","itemSizes":[],"itemBrand":null,"itemPromotions":[],"shopName":"","itemSize":null,"shippingMethodId":"14","categoryId":"7015","isNoPrice":false,"title":"","isLiked":false,"photos":[{"uri":"https://static.mercdn.net/item/detail/webp/photos/m29051587548_1.jpg?1775870311"}],"auction":null,"shop":null,"attributes":[]},{"id":"m97317254760","sellerId":"872025009","buyerId":"","status":"ITEM_STATUS_SOLD_OUT","name":"ドラゴンクエストVII Reimagined ドラクエ7 リメイク","price":"6100","created":"1771911254","updated":"1772002920","thumbnails":["https://static.mercdn.net/thumb/item/webp/m97317254760_1.jpg?1771911254"],"itemType":"ITEM_TYPE_MERCARI","itemConditionId":"3","shippingPayerId":"2","itemSizes":[],"itemBrand":null,"itemPromotions":[],"shopName":"","itemSize":null,"shippingMethodId":"17","categoryId":"7015","isNoPrice":false,"title":"","isLiked":false,"photos":[{"uri":"https://static.mercdn.net/item/detail/webp/photos/m97317254760_1.jpg?1771911254"}],"auction":null,"shop":null,"attributes":[]},{"id":"m42819988805","sellerId":"964007628","buyerId":"","status":"ITEM_STATUS_SOLD_OUT","name":"ドラゴンクエストVII リメイク Nintendo Switch","price":"4300","created":"1774666824","updated":"1776952986","thumbnails":["https://static.mercdn.net/thumb/item/webp/m42819988805_1.jpg?1774666824"],"itemType":"ITEM_TYPE_MERCARI","itemConditionId":"3","shippingPayerId":"2","itemSizes":[],"itemBrand":null,"itemPromotions":[],"shopName":"","itemSize":null,"shippingMethodId":"14","categoryId":"7015","isNoPrice":false,"title":"","isLiked":false,"photos":[{"uri":"https://static.mercdn.net/item/detail/webp/photos/m42819988805_1.jpg?1774666824"}],"auction":null,"shop":null,"attributes":[]},{"id":"m55309936885","sellerId":"196400149","buyerId":"","status":"ITEM_STATUS_SOLD_OUT","name":"【Switch2】ドラゴンクエストVII リメイク","price":"5300","created":"1773482193","updated":"1773755342","thumbnails":["https://static.mercdn.net/thumb/item/webp/m55309936885_1.jpg?1773482193"],"itemType":"ITEM_TYPE_MERCARI","itemConditionId":"3","shippingPayerId":"2","itemSizes":[],"itemBrand":null,"itemPromotions":[],"shopName":"","itemSize":null,"shippingMethodId":"14","categoryId":"7015","isNoPrice":false,"title":"","isLiked":false,"photos":[{"uri":"https://static.mercdn.net/item/detail/webp/photos/m55309936885_1.jpg?1773482193"}],"auction":null,"shop":null,"attributes":[]},{"id":"m55347553319","sellerId":"689083248","buyerId":"","status":"ITEM_STATUS_SOLD_OUT","name":"ドラゴンクエストVIII リメイク Nintendo Switch2","price":"4800","created":"1775212909","updated":"1775872441","thumbnails":["https://static.mercdn.net/thumb/item/webp/m55347553319_1.jpg?1775212909"],"itemType":"ITEM_TYPE_MERCARI","itemConditionId":"3","shippingPayerId":"2","itemSizes":[],"itemBrand":null,"itemPromotions":[],"shopName":"","itemSize":null,"shippingMethodId":"14","categoryId":"7015","isNoPrice":false,"title":"","isLiked":false,"photos":[{"uri":"https://static.mercdn.net/item/detail/webp/photos/m55347553319_1.jpg?1775212909"}],"auction":null,"shop":null,"attributes":[]}],"components":[],"searchCondition":null,"searchConditionId":""}
