{"result":"OK","data":{"id":"m46755832731","seller":{"id":933962339,"name":"ら","photo_url":"https://static.mercdn.net/members/resized/webp/933962339.jpg?1758426507","photo_thumbnail_url":"https://static.mercdn.net/thumb/members/webp/933962339.jpg?1758426507","register_sms_confirmation":"yes","register_sms_confirmation_at":"2021-01-04 20:54:23","created":1570370088,"num_sell_items":133,"ratings":{"good":217,"normal":0,"bad":2},"num_ratings":219,"score":215,"is_official":false,"quick_shipper":true,"is_followable":true,"is_blocked":false,"is_inactive":false,"star_rating_score":5},"status":"sold_out","name":"ドラゴンクエストVII エデンの戦士たち - Reimaginedドラクエ7","price":5300,"description":"Nintendo Switch用のドラゴンクエストVIIのリメイク版、魅力的なキャラクターと冒険が楽しめる。\n起動確認済みです。\nドラクエ7 リメイク\n\n- タイトル: ドラゴンクエストVII エデンの戦士たち - Reimagined\n- CEROレーティング: B\n- 開発会社: SQUARE ENIX\n- プラットフォーム: Nintendo Switch\n\nご覧いただきありがとうございます。","photos":["https://static.mercdn.net/item/detail/orig/photos/m46755832731_1.jpg?1774407556","https://static.mercdn.net/item/detail/orig/photos/m46755832731_2.jpg?1774407556","https://static.mercdn.net/item/detail/orig/photos/m46755832731_3.jpg?1774407556","https://static.mercdn.net/item/detail/orig/photos/m46755832731_4.jpg?1774407556","https://static.mercdn.net/item/detail/orig/photos/m46755832731_5.jpg?1774407556","https://static.mercdn.net/item/detail/orig/photos/m46755832731_6.jpg?1774407556"],"photo_paths":["photos/m46755832731_1.jpg","photos/m46755832731_2.jpg","photos/m46755832731_3.jpg","photos/m46755832731_4.jpg","photos/m46755832731_5.jpg","photos/m46755832731_6.jpg"],"thumbnails":["https://static.mercdn.net/thumb/item/jpeg/m46755832731_1.jpg?1774407556"],"item_category":{"id":7002,"name":"Nintendo Switch","display_order":10,"parent_category_id":76,"parent_category_name":"テレビゲーム","root_category_id":1328,"root_category_name":"ゲーム・おもちゃ・グッズ"},"item_category_ntiers":{"id":702,"name":"ソフト(パッケージ版)","display_order":4,"parent_category_id":7002,"parent_category_name":"Nintendo Switch","root_category_id":1328,"root_category_name":"ゲーム・おもちゃ・グッズ","brand_group_id":1},"parent_categories_ntiers":[{"id":1328,"name":"ゲーム・おもちゃ・グッズ","display_order":0},{"id":76,"name":"テレビゲーム","display_order":0},{"id":7002,"name":"Nintendo Switch","display_order":0}],"item_condition":{"id":2,"name":"未使用に近い","subname":"数回使用し、あまり使用感がない"},"item_brand":{"id":7138,"name":"SQUARE ENIX","sub_name":"SQUARE ENIX"},"colors":[],"shipping_payer":{"id":2,"name":"送料込み(出品者負担)","code":"seller"},"shipping_method":{"id":14,"name":"らくらくメルカリ便","is_deprecated":"no"},"shipping_from_area":{"id":13,"name":"東京都"},"shipping_duration":{"id":1,"name":"1~2日で発送","min_days":1,"max_days":2},"shipping_class":{"id":1,"name":"ネコポス","description":"ネコポス","fee":210,"carrier":"yamato","carrier_display_name":"ヤマト運輸","request_class_display_name":"ネコポス","icon_id":0,"pickup_fee":0,"shipping_fee":210,"total_fee":210,"is_pickup":false},"num_likes":1,"num_comments":0,"registered_prices_count":0,"comments":[],"updated":1774615019,"created":1774407556,"pager_id":5743688651,"liked":false,"checksum":"9d46994eaf7b24467579bffde58c10dc","is_dynamic_shipping_fee":false,"application_attributes":{},"is_shop_item":"no","hash_tags":[],"is_anonymous_shipping":true,"is_web_visible":true,"is_offerable":false,"is_organizational_user":false,"organizational_user_status":"","is_stock_item":false,"is_cancelable":true,"shipped_by_worker":false,"transaction_evidence":{"id":2199527886,"status":"done"},"additional_services":[],"has_additional_service":false,"has_like_list":false,"is_offerable_v2":false,"is_dismissed":false,"meta_title":"ドラゴンクエストVII エデンの戦士たち - Reimaginedドラクエ7","meta_subtitle":"SQUARE ENIX・未使用に近い","is_degraded":false},"meta":{}}
