{"result":"OK","data":{"id":"m17880891165","seller":{"id":116814416,"name":"yukimi","photo_url":"https://static.mercdn.net/members/resized/webp/116814416.jpg?1574603616","photo_thumbnail_url":"https://static.mercdn.net/thumb/members/webp/116814416.jpg?1574603616","register_sms_confirmation":"yes","register_sms_confirmation_at":"2019-11-18 19:47:14","created":1573952593,"num_sell_items":106,"ratings":{"good":158,"normal":0,"bad":0},"num_ratings":158,"score":158,"is_official":false,"quick_shipper":true,"is_followable":true,"is_blocked":false,"is_inactive":false,"star_rating_score":5},"status":"sold_out","name":"コード未使用 ドラゴンクエストVII PS5 Reimagined","price":4180,"description":"PlayStation 5向けのドラゴンクエストVIIです。\r\nPS5 ドラクエ7 Reimagined\r\n\r\nプロダクトコード未使用確認済みです。\r\nお値引きは適宜行いますので交渉はご遠慮ください。\r\n\r\nペットやタバコは吸いません、CDもきれいだと思います。\r\n\r\n名作です。ここ数年で一番良いドラクエリメイクでした。\r\n昔プレステで7をプレイされた人は確実に満足できると思います。\r\n\r\n- タイトル: ドラゴンクエストVII リメイク\r\n- プラットフォーム: PlayStation 5\r\n- CEROレーティング: B\r\n- メーカー: SQUARE ENIX","photos":["https://static.mercdn.net/item/detail/orig/photos/m17880891165_1.jpg?1775711635","https://static.mercdn.net/item/detail/orig/photos/m17880891165_2.jpg?1775711635"],"photo_paths":["photos/m17880891165_1.jpg","photos/m17880891165_2.jpg"],"thumbnails":["https://static.mercdn.net/thumb/item/jpeg/m17880891165_1.jpg?1775711635"],"item_category":{"id":6983,"name":"プレイステーション5(PS5)","display_order":40,"parent_category_id":76,"parent_category_name":"テレビゲーム","root_category_id":1328,"root_category_name":"ゲーム・おもちゃ・グッズ"},"item_category_ntiers":{"id":6985,"name":"ソフト(パッケージ版)","display_order":3,"parent_category_id":6983,"parent_category_name":"プレイステーション5(PS5)","root_category_id":1328,"root_category_name":"ゲーム・おもちゃ・グッズ","brand_group_id":1},"parent_categories_ntiers":[{"id":1328,"name":"ゲーム・おもちゃ・グッズ","display_order":0},{"id":76,"name":"テレビゲーム","display_order":0},{"id":6983,"name":"プレイステーション5(PS5)","display_order":0}],"item_condition":{"id":2,"name":"未使用に近い","subname":"数回使用し、あまり使用感がない"},"item_brand":{"id":17543,"name":"PlayStation5","sub_name":"PlayStation5"},"colors":[],"shipping_payer":{"id":2,"name":"送料込み(出品者負担)","code":"seller"},"shipping_method":{"id":14,"name":"らくらくメルカリ便","is_deprecated":"no"},"shipping_from_area":{"id":13,"name":"東京都"},"shipping_duration":{"id":1,"name":"1~2日で発送","min_days":1,"max_days":2},"shipping_class":{"id":1,"name":"ネコポス","description":"ネコポス","fee":210,"carrier":"yamato","carrier_display_name":"ヤマト運輸","request_class_display_name":"ネコポス","icon_id":0,"pickup_fee":0,"shipping_fee":210,"total_fee":210,"is_pickup":false},"num_likes":1,"num_comments":0,"registered_prices_count":0,"comments":[],"updated":1775890186,"created":1775711635,"pager_id":5747600888,"liked":false,"checksum":"0f41ad76afe8d5447c3ac221c5239cc0","is_dynamic_shipping_fee":false,"application_attributes":{},"is_shop_item":"no","hash_tags":[],"is_anonymous_shipping":true,"is_web_visible":true,"is_offerable":false,"is_organizational_user":false,"organizational_user_status":"","is_stock_item":false,"is_cancelable":true,"shipped_by_worker":false,"transaction_evidence":{"id":2211916624,"status":"done"},"additional_services":[],"has_additional_service":false,"has_like_list":false,"is_offerable_v2":false,"is_dismissed":false,"meta_title":"コード未使用 ドラゴンクエストVII PS5 Reimagined","meta_subtitle":"PlayStation5・未使用に近い","is_degraded":false},"meta":{}}
