{"result":"OK","data":{"id":"m79070814508","seller":{"id":951810010,"name":"りぬ","photo_url":"https://static.mercdn.net/members/resized/webp/951810010.jpg?1498566638","photo_thumbnail_url":"https://static.mercdn.net/thumb/members/webp/951810010.jpg?1498566638","register_sms_confirmation":"yes","register_sms_confirmation_at":"2021-10-09 17:42:52","created":1437547233,"num_sell_items":85,"ratings":{"good":377,"normal":0,"bad":1},"num_ratings":378,"score":376,"is_official":false,"quick_shipper":false,"is_followable":true,"is_blocked":false,"is_inactive":false,"star_rating_score":5},"status":"on_sale","name":"ファイナルファンタジー7リメイク インターグレード","price":5777,"description":"「ファイナルファンタジー7リメイク インターグレード」\n定価: ￥ 8980\n\nFINAL FANTASY VII REMAKE INTERGRADE PS5版\n\n動作確認済\n即購入可\n\n状態は写真をご確認ください。\n\n#ゲーム #RPG #PlayStation5 #PlayStation_5 #PS5","photos":["https://static.mercdn.net/item/detail/orig/photos/m79070814508_1.jpg?1702216442","https://static.mercdn.net/item/detail/orig/photos/m79070814508_2.jpg?1702216442"],"photo_paths":["photos/m79070814508_1.jpg","photos/m79070814508_2.jpg"],"thumbnails":["https://static.mercdn.net/thumb/item/jpeg/m79070814508_1.jpg?1702216442"],"item_category":{"id":7002,"name":"Nintendo Switch","display_order":10,"parent_category_id":76,"parent_category_name":"テレビゲーム","root_category_id":1328,"root_category_name":"ゲーム・おもちゃ・グッズ"},"item_category_ntiers":{"id":702,"name":"ソフト(パッケージ版)","display_order":4,"parent_category_id":7002,"parent_category_name":"Nintendo Switch","root_category_id":1328,"root_category_name":"ゲーム・おもちゃ・グッズ","brand_group_id":1},"parent_categories_ntiers":[{"id":1328,"name":"ゲーム・おもちゃ・グッズ","display_order":0},{"id":76,"name":"テレビゲーム","display_order":0},{"id":7002,"name":"Nintendo Switch","display_order":0}],"item_condition":{"id":3,"name":"目立った傷や汚れなし","subname":"細かな使用感・傷・汚れはあるが、目立たない"},"item_brand":{"id":17543,"name":"PlayStation5","sub_name":"PlayStation5"},"colors":[],"shipping_payer":{"id":2,"name":"送料込み(出品者負担)","code":"seller"},"shipping_method":{"id":14,"name":"らくらくメルカリ便","is_deprecated":"no"},"shipping_from_area":{"id":9,"name":"栃木県"},"shipping_duration":{"id":1,"name":"1~2日で発送","min_days":1,"max_days":2},"shipping_class":{"id":0,"fee":0,"icon_id":0,"pickup_fee":0,"shipping_fee":0,"total_fee":0,"is_pickup":false},"num_likes":1,"num_comments":3,"registered_prices_count":0,"comments":[{"id":579539117258119759,"user":{"id":171197552,"name":"ハラピ","photo_url":"https://static.mercdn.net/images/member_photo_noimage.png","photo_thumbnail_url":"https://static.mercdn.net/images/member_photo_noimage_thumb.png"},"message":"了解しました。ありがとうございます。","created":1709935720},{"id":6484865970620562658,"user":{"id":951810010,"name":"りぬ","photo_url":"https://static.mercdn.net/members/resized/webp/951810010.jpg?1498566638","photo_thumbnail_url":"https://static.mercdn.net/thumb/members/webp/951810010.jpg?1498566638"},"message":"コメントありがとうございます。DLCについては記憶がおぼろげではあるのですが、使用済みと思われます。","created":1709913049},{"id":2822482638000506718,"user":{"id":171197552,"name":"ハラピ","photo_url":"https://static.mercdn.net/images/member_photo_noimage.png","photo_thumbnail_url":"https://static.mercdn.net/images/member_photo_noimage_thumb.png"},"message":"質問いたします。DLCは使用済みでしょうか？","created":1709863233}],"updated":1702216442,"created":1702216442,"pager_id":5527115309,"liked":false,"checksum":"7e511c96c2082b442398a1dd614a38fe","is_dynamic_shipping_fee":false,"application_attributes":{},"is_shop_item":"no","hash_tags":["ゲーム","RPG","PlayStation5","PlayStation_5","PS5"],"is_anonymous_shipping":true,"is_web_visible":true,"is_offerable":false,"is_organizational_user":false,"organizational_user_status":"","is_stock_item":false,"is_cancelable":true,"shipped_by_worker":false,"additional_services":[],"has_additional_service":false,"has_like_list":false,"is_offerable_v2":false,"is_dismissed":false,"meta_title":"ファイナルファンタジー7リメイク インターグレード","meta_subtitle":"PlayStation5・目立った傷や汚れなし","is_degraded":false},"meta":{}}
