{"result":"OK","data":{"id":"m31036784717","seller":{"id":116449920,"name":"こんぺいとう","photo_url":"https://static.mercdn.net/members/resized/webp/116449920.jpg?1771001400","photo_thumbnail_url":"https://static.mercdn.net/thumb/members/webp/116449920.jpg?1771001400","register_sms_confirmation":"yes","register_sms_confirmation_at":"2023-01-07 20:26:04","created":1673090764,"num_sell_items":14,"ratings":{"good":34,"normal":0,"bad":0},"num_ratings":34,"score":34,"is_official":false,"quick_shipper":false,"is_followable":true,"is_blocked":false,"is_inactive":false,"star_rating_score":5},"status":"sold_out","name":"FINAL FANTASY VII REMAKE INTERGRADE","price":4350,"description":"アクションRPGの名作、FINAL FANTASY VII REMAKE INTERGRADEがNintendo Switchで登場。\n\n- タイトル: FINAL FANTASY VII REMAKE INTERGRADE\n- プラットフォーム: Nintendo Switch\n- CEROレーティング: C\n- 発売元: SQUARE ENIX\n- ゲームジャンル: アクションRPG\n- キャラクター: クラウド・ストライフ\n値下げ❌\nご覧いただきありがとうございます。","photos":["https://static.mercdn.net/item/detail/orig/photos/m31036784717_1.jpg?1779878430","https://static.mercdn.net/item/detail/orig/photos/m31036784717_2.jpg?1779878430","https://static.mercdn.net/item/detail/orig/photos/m31036784717_3.jpg?1779878430","https://static.mercdn.net/item/detail/orig/photos/m31036784717_4.jpg?1779878430","https://static.mercdn.net/item/detail/orig/photos/m31036784717_5.jpg?1779878430"],"photo_paths":["photos/m31036784717_1.jpg","photos/m31036784717_2.jpg","photos/m31036784717_3.jpg","photos/m31036784717_4.jpg","photos/m31036784717_5.jpg"],"thumbnails":["https://static.mercdn.net/thumb/item/jpeg/m31036784717_1.jpg?1779878430"],"item_category":{"id":7013,"name":"Nintendo Switch 2","display_order":9,"parent_category_id":76,"parent_category_name":"テレビゲーム","root_category_id":1328,"root_category_name":"ゲーム・おもちゃ・グッズ","brand_group_id":1},"item_category_ntiers":{"id":7015,"name":"ソフト(パッケージ版)","display_order":2,"parent_category_id":7013,"parent_category_name":"Nintendo Switch 2","root_category_id":1328,"root_category_name":"ゲーム・おもちゃ・グッズ","brand_group_id":1},"parent_categories_ntiers":[{"id":1328,"name":"ゲーム・おもちゃ・グッズ","display_order":0},{"id":76,"name":"テレビゲーム","display_order":0},{"id":7013,"name":"Nintendo Switch 2","display_order":0}],"item_condition":{"id":3,"name":"目立った傷や汚れなし","subname":"細かな使用感・傷・汚れはあるが、目立たない"},"colors":[],"shipping_payer":{"id":2,"name":"送料込み(出品者負担)","code":"seller"},"shipping_method":{"id":14,"name":"らくらくメルカリ便","is_deprecated":"no"},"shipping_from_area":{"id":13,"name":"東京都"},"shipping_duration":{"id":2,"name":"2~3日で発送","min_days":2,"max_days":3},"shipping_class":{"id":1,"name":"ネコポス","description":"ネコポス","fee":210,"carrier":"yamato","carrier_display_name":"ヤマト運輸","request_class_display_name":"ネコポス","icon_id":0,"pickup_fee":0,"shipping_fee":210,"total_fee":210,"is_pickup":false},"num_likes":1,"num_comments":3,"registered_prices_count":0,"comments":[{"id":2094230887534886446,"user":{"id":116449920,"name":"こんぺいとう","photo_url":"https://static.mercdn.net/members/resized/webp/116449920.jpg?1771001400","photo_thumbnail_url":"https://static.mercdn.net/thumb/members/webp/116449920.jpg?1771001400"},"message":"和哉様4350円でも可能でしょうか?","created":1780124241},{"id":5075025804527154265,"user":{"id":961435609,"name":"和哉","photo_url":"https://static.mercdn.net/members/resized/webp/961435609.jpg?1493206609","photo_thumbnail_url":"https://static.mercdn.net/thumb/members/webp/961435609.jpg?1493206609"},"message":"コメント失礼します。\n4,300円で購入させて頂きたいです。\n値引きの方可能ですか？","created":1780104537},{"id":5133696137079852412,"user":{"id":596711378,"name":"ちく 〜取引時プロフィール必読ください〜","photo_url":"https://static.mercdn.net/members/resized/webp/596711378.jpg?1764853005","photo_thumbnail_url":"https://static.mercdn.net/thumb/members/webp/596711378.jpg?1764853005"},"message":"コメント失礼致します。\n購入検討していますが、下記の通り値引きいただけないでしょうか？\n\n■ご提案金額\n4,000円\n\n■根拠\n・現在メルカリ内の最安値が4,085円であること\n・超メルカリ市の施策により、平時より送料・手数料が安くなること\n\n★手数料\n明日30日にエントリーの上出品すると、出品手数料が半額ポイント還元となります。\n仮に4,000円で販売すると200円分ポイント還元となるため、平時より200円お得です。\n\n★送料\nポスト投函の配送方法が一律150円となるため、平時より60円お得です。\n\n4,000円まで値引きしますとある程度出品者様にご負担となりますが、値引き額のおよそ3分の1はメルカリの施策にてまかなえるご提案です。\nご検討いただけますと幸いです。","created":1780044885}],"updated":1780288038,"created":1779878430,"pager_id":5760101273,"liked":false,"checksum":"46ec7f2d576cfc34403130009861e2c0","is_dynamic_shipping_fee":false,"application_attributes":{},"is_shop_item":"no","hash_tags":[],"is_anonymous_shipping":true,"is_web_visible":true,"is_offerable":false,"is_organizational_user":false,"organizational_user_status":"","is_stock_item":false,"is_cancelable":true,"shipped_by_worker":false,"transaction_evidence":{"id":2252557775,"status":"done"},"additional_services":[],"has_additional_service":false,"has_like_list":false,"is_offerable_v2":false,"is_dismissed":false,"meta_title":"FINAL FANTASY VII REMAKE INTERGRADE","meta_subtitle":"目立った傷や汚れなし","is_degraded":false},"meta":{}}
