{"result":"OK","data":{"id":"m20549031706","seller":{"id":934470604,"name":"♡IGAL福☆桜ASO♡即購入OK","photo_url":"https://static.mercdn.net/members/resized/webp/934470604.jpg?1750751682","photo_thumbnail_url":"https://static.mercdn.net/thumb/members/webp/934470604.jpg?1750751682","register_sms_confirmation":"yes","register_sms_confirmation_at":"2021-02-13 20:59:05","created":1613217545,"num_sell_items":4347,"ratings":{"good":2886,"normal":0,"bad":1},"num_ratings":2887,"score":2885,"is_official":false,"quick_shipper":false,"is_followable":true,"is_blocked":false,"is_inactive":false,"star_rating_score":5},"status":"sold_out","name":"Switch2 ファイナルファンタジー7 リメイクインターグレード キーカード版","price":4777,"description":"目立つ傷や汚れなどないと思いますがトラブル防止の為神経質な方はご購入お控え下さい。\n\nプチプチ封筒に入れ匿名配送予定です。\n\n早期購入特典はありませんのでご理解いただける方のご購入お願いいたします。","photos":["https://static.mercdn.net/item/detail/orig/photos/m20549031706_1.jpg?1770100937","https://static.mercdn.net/item/detail/orig/photos/m20549031706_2.jpg?1770100937","https://static.mercdn.net/item/detail/orig/photos/m20549031706_3.jpg?1770100937","https://static.mercdn.net/item/detail/orig/photos/m20549031706_4.jpg?1770100937"],"photo_paths":["photos/m20549031706_1.jpg","photos/m20549031706_2.jpg","photos/m20549031706_3.jpg","photos/m20549031706_4.jpg"],"thumbnails":["https://static.mercdn.net/thumb/item/jpeg/m20549031706_1.jpg?1770100937"],"item_category":{"id":7013,"name":"Nintendo Switch 2","display_order":9,"parent_category_id":76,"parent_category_name":"テレビゲーム","root_category_id":1328,"root_category_name":"ゲーム・おもちゃ・グッズ","brand_group_id":1},"item_category_ntiers":{"id":7015,"name":"ソフト(パッケージ版)","display_order":2,"parent_category_id":7013,"parent_category_name":"Nintendo Switch 2","root_category_id":1328,"root_category_name":"ゲーム・おもちゃ・グッズ","brand_group_id":1},"parent_categories_ntiers":[{"id":1328,"name":"ゲーム・おもちゃ・グッズ","display_order":0},{"id":76,"name":"テレビゲーム","display_order":0},{"id":7013,"name":"Nintendo Switch 2","display_order":0}],"item_condition":{"id":2,"name":"未使用に近い","subname":"数回使用し、あまり使用感がない"},"colors":[],"shipping_payer":{"id":2,"name":"送料込み(出品者負担)","code":"seller"},"shipping_method":{"id":17,"name":"ゆうゆうメルカリ便","is_deprecated":"no"},"shipping_from_area":{"id":99,"name":"未定"},"shipping_duration":{"id":2,"name":"2~3日で発送","min_days":2,"max_days":3},"shipping_class":{"id":32,"name":"ゆうパケットポスト","description":"ゆうパケットポスト","fee":215,"carrier":"japan_post","carrier_display_name":"日本郵便","request_class_display_name":"ゆうパケットポスト","icon_id":0,"pickup_fee":0,"shipping_fee":215,"total_fee":215,"is_pickup":false},"num_likes":2,"num_comments":0,"registered_prices_count":0,"comments":[],"updated":1770421218,"created":1770100937,"pager_id":5730768794,"liked":false,"checksum":"c395d473a272e131668976cfd0d02182","is_dynamic_shipping_fee":false,"application_attributes":{},"is_shop_item":"no","hash_tags":[],"is_anonymous_shipping":true,"is_web_visible":true,"is_offerable":false,"is_organizational_user":false,"organizational_user_status":"","is_stock_item":false,"is_cancelable":true,"shipped_by_worker":false,"transaction_evidence":{"id":2159689161,"status":"done"},"additional_services":[],"has_additional_service":false,"delivery_facility_type":"japan_post","has_like_list":false,"is_offerable_v2":false,"is_dismissed":false,"meta_title":"Switch2 ファイナルファンタジー7 リメイクインターグレード キーカード版","meta_subtitle":"未使用に近い","is_degraded":false},"meta":{}}
