{"meta":{"nextPageToken":"","previousPageToken":"v1:3","numFound":"518","properties":[]},"items":[{"id":"m48242171835","sellerId":"355266330","buyerId":"","status":"ITEM_STATUS_TRADING","name":"プラグマタ　Switch2 PRAGMATA","price":"5800","created":"1781746210","updated":"1781914396","thumbnails":["https://static.mercdn.net/thumb/item/webp/m48242171835_1.jpg?1781746764"],"itemType":"ITEM_TYPE_MERCARI","itemConditionId":"2","shippingPayerId":"2","itemSizes":[],"itemBrand":null,"itemPromotions":[],"shopName":"","itemSize":null,"shippingMethodId":"17","categoryId":"7015","isNoPrice":false,"title":"","isLiked":false,"photos":[{"uri":"https://static.mercdn.net/item/detail/webp/photos/m48242171835_1.jpg?1781746764"}],"auction":null,"shop":null,"attributes":[]},{"id":"m28853079806","sellerId":"167627704","buyerId":"","status":"ITEM_STATUS_SOLD_OUT","name":"【特典未使用】プラグマタ Nintendo Switch2ソフト","price":"5600","created":"1781400625","updated":"1781561254","thumbnails":["https://static.mercdn.net/thumb/item/webp/m28853079806_1.jpg?1781400625"],"itemType":"ITEM_TYPE_MERCARI","itemConditionId":"2","shippingPayerId":"2","itemSizes":[],"itemBrand":null,"itemPromotions":[],"shopName":"","itemSize":null,"shippingMethodId":"14","categoryId":"7015","isNoPrice":false,"title":"","isLiked":false,"photos":[{"uri":"https://static.mercdn.net/item/detail/webp/photos/m28853079806_1.jpg?1781400625"}],"auction":null,"shop":null,"attributes":[]},{"id":"m32986200805","sellerId":"672621424","buyerId":"","status":"ITEM_STATUS_TRADING","name":"PRAGMATA プラグマタ Switch2版","price":"5500","created":"1781792575","updated":"1781825330","thumbnails":["https://static.mercdn.net/thumb/item/webp/m32986200805_1.jpg?1781792575"],"itemType":"ITEM_TYPE_MERCARI","itemConditionId":"3","shippingPayerId":"2","itemSizes":[],"itemBrand":null,"itemPromotions":[],"shopName":"","itemSize":null,"shippingMethodId":"14","categoryId":"7015","isNoPrice":false,"title":"","isLiked":false,"photos":[{"uri":"https://static.mercdn.net/item/detail/webp/photos/m32986200805_1.jpg?1781792575"}],"auction":null,"shop":null,"attributes":[]},{"id":"m79840626924","sellerId":"141433051","buyerId":"","status":"ITEM_STATUS_TRADING","name":"ま*匠様 プラグマタ PRAGMATA Switch2 早期購入特典未使用","price":"5600","created":"1781762989","updated":"1781869229","thumbnails":["https://static.mercdn.net/thumb/item/webp/m79840626924_1.jpg?1781762989"],"itemType":"ITEM_TYPE_MERCARI","itemConditionId":"3","shippingPayerId":"2","itemSizes":[],"itemBrand":null,"itemPromotions":[],"shopName":"","itemSize":null,"shippingMethodId":"14","categoryId":"7015","isNoPrice":false,"title":"","isLiked":false,"photos":[{"uri":"https://static.mercdn.net/item/detail/webp/photos/m79840626924_1.jpg?1781762989"}],"auction":null,"shop":null,"attributes":[]},{"id":"m55419406385","sellerId":"701260719","buyerId":"","status":"ITEM_STATUS_SOLD_OUT","name":"プラグマタ PRAGMATA Switch2 ソフト","price":"5800","created":"1781340468","updated":"1781624493","thumbnails":["https://static.mercdn.net/thumb/item/webp/m55419406385_1.jpg?1781340468"],"itemType":"ITEM_TYPE_MERCARI","itemConditionId":"2","shippingPayerId":"2","itemSizes":[],"itemBrand":null,"itemPromotions":[],"shopName":"","itemSize":null,"shippingMethodId":"14","categoryId":"7015","isNoPrice":false,"title":"","isLiked":false,"photos":[{"uri":"https://static.mercdn.net/item/detail/webp/photos/m55419406385_1.jpg?1781340468"}],"auction":null,"shop":null,"attributes":[]},{"id":"m52894915967","sellerId":"595461264","buyerId":"","status":"ITEM_STATUS_SOLD_OUT","name":"プラグマタ　応募券　懸賞　Switch2 PS5 ゲーム　Vジャンプ　30枚","price":"669","created":"1772120199","updated":"1772864586","thumbnails":["https://static.mercdn.net/thumb/item/webp/m52894915967_1.jpg?1772120265"],"itemType":"ITEM_TYPE_MERCARI","itemConditionId":"3","shippingPayerId":"2","itemSizes":[],"itemBrand":null,"itemPromotions":[],"shopName":"","itemSize":null,"shippingMethodId":"17","categoryId":"10165","isNoPrice":false,"title":"","isLiked":false,"photos":[{"uri":"https://static.mercdn.net/item/detail/webp/photos/m52894915967_1.jpg?1772120265"}],"auction":null,"shop":null,"attributes":[]},{"id":"m28187822221","sellerId":"683019098","buyerId":"","status":"ITEM_STATUS_SOLD_OUT","name":"Switch2 プラグマタ","price":"5600","created":"1781517586","updated":"1781698212","thumbnails":["https://static.mercdn.net/thumb/item/webp/m28187822221_1.jpg?1781517586"],"itemType":"ITEM_TYPE_MERCARI","itemConditionId":"3","shippingPayerId":"2","itemSizes":[],"itemBrand":null,"itemPromotions":[],"shopName":"","itemSize":null,"shippingMethodId":"17","categoryId":"7015","isNoPrice":false,"title":"","isLiked":false,"photos":[{"uri":"https://static.mercdn.net/item/detail/webp/photos/m28187822221_1.jpg?1781517586"}],"auction":null,"shop":null,"attributes":[]},{"id":"m27933515822","sellerId":"652702289","buyerId":"","status":"ITEM_STATUS_SOLD_OUT","name":"PRAGMATA プラグマタ Nintendo Switch2 ソフト","price":"5800","created":"1780826911","updated":"1781202502","thumbnails":["https://static.mercdn.net/thumb/item/webp/m27933515822_1.jpg?1780826911"],"itemType":"ITEM_TYPE_MERCARI","itemConditionId":"3","shippingPayerId":"2","itemSizes":[],"itemBrand":null,"itemPromotions":[],"shopName":"","itemSize":null,"shippingMethodId":"14","categoryId":"7015","isNoPrice":false,"title":"","isLiked":false,"photos":[{"uri":"https://static.mercdn.net/item/detail/webp/photos/m27933515822_1.jpg?1780826911"}],"auction":null,"shop":null,"attributes":[]},{"id":"m59699213338","sellerId":"412613196","buyerId":"","status":"ITEM_STATUS_SOLD_OUT","name":"プラグマタ　Switch2版","price":"6850","created":"1777212946","updated":"1777572635","thumbnails":["https://static.mercdn.net/thumb/item/webp/m59699213338_1.jpg?1777212946"],"itemType":"ITEM_TYPE_MERCARI","itemConditionId":"2","shippingPayerId":"2","itemSizes":[],"itemBrand":null,"itemPromotions":[],"shopName":"","itemSize":null,"shippingMethodId":"17","categoryId":"7015","isNoPrice":false,"title":"","isLiked":false,"photos":[{"uri":"https://static.mercdn.net/item/detail/webp/photos/m59699213338_1.jpg?1777212946"}],"auction":null,"shop":null,"attributes":[]},{"id":"m20113375601","sellerId":"410608542","buyerId":"","status":"ITEM_STATUS_SOLD_OUT","name":"【Switch2】 プラグマタ [通常版] 早期購入特典未使用","price":"6088","created":"1781080565","updated":"1781343836","thumbnails":["https://static.mercdn.net/thumb/item/webp/m20113375601_1.jpg?1781080565"],"itemType":"ITEM_TYPE_MERCARI","itemConditionId":"3","shippingPayerId":"2","itemSizes":[],"itemBrand":null,"itemPromotions":[],"shopName":"","itemSize":null,"shippingMethodId":"17","categoryId":"7015","isNoPrice":false,"title":"","isLiked":false,"photos":[{"uri":"https://static.mercdn.net/item/detail/webp/photos/m20113375601_1.jpg?1781080565"}],"auction":null,"shop":null,"attributes":[]},{"id":"m71231036874","sellerId":"542496148","buyerId":"","status":"ITEM_STATUS_SOLD_OUT","name":"プラグマタ　Nintendo Switch2","price":"5700","created":"1781227806","updated":"1781430489","thumbnails":["https://static.mercdn.net/thumb/item/webp/m71231036874_1.jpg?1781227806"],"itemType":"ITEM_TYPE_MERCARI","itemConditionId":"3","shippingPayerId":"2","itemSizes":[],"itemBrand":null,"itemPromotions":[],"shopName":"","itemSize":null,"shippingMethodId":"14","categoryId":"7015","isNoPrice":false,"title":"","isLiked":false,"photos":[{"uri":"https://static.mercdn.net/item/detail/webp/photos/m71231036874_1.jpg?1781227806"}],"auction":null,"shop":null,"attributes":[]},{"id":"m24843552591","sellerId":"420963203","buyerId":"","status":"ITEM_STATUS_SOLD_OUT","name":"プラグマタ PRAGMATA switch2","price":"5900","created":"1779611945","updated":"1780375852","thumbnails":["https://static.mercdn.net/thumb/item/webp/m24843552591_1.jpg?1779611945"],"itemType":"ITEM_TYPE_MERCARI","itemConditionId":"2","shippingPayerId":"2","itemSizes":[],"itemBrand":null,"itemPromotions":[],"shopName":"","itemSize":null,"shippingMethodId":"17","categoryId":"7015","isNoPrice":false,"title":"","isLiked":false,"photos":[{"uri":"https://static.mercdn.net/item/detail/webp/photos/m24843552591_1.jpg?1779611945"}],"auction":null,"shop":null,"attributes":[]},{"id":"m18533034724","sellerId":"334694165","buyerId":"","status":"ITEM_STATUS_TRADING","name":"Switch2 プラグマタ　プロダクトコード未使用","price":"5300","created":"1781906477","updated":"1782008878","thumbnails":["https://static.mercdn.net/thumb/item/webp/m18533034724_1.jpg?1781906477"],"itemType":"ITEM_TYPE_MERCARI","itemConditionId":"2","shippingPayerId":"2","itemSizes":[],"itemBrand":null,"itemPromotions":[],"shopName":"","itemSize":null,"shippingMethodId":"17","categoryId":"7015","isNoPrice":false,"title":"","isLiked":false,"photos":[{"uri":"https://static.mercdn.net/item/detail/webp/photos/m18533034724_1.jpg?1781906477"}],"auction":null,"shop":null,"attributes":[]},{"id":"m13449050590","sellerId":"493603562","buyerId":"","status":"ITEM_STATUS_TRADING","name":"PRAGMATA プラグマタ　Nintendo Switch2 ソフト","price":"5600","created":"1781767214","updated":"1781775754","thumbnails":["https://static.mercdn.net/thumb/item/webp/m13449050590_1.jpg?1781767214"],"itemType":"ITEM_TYPE_MERCARI","itemConditionId":"3","shippingPayerId":"2","itemSizes":[],"itemBrand":null,"itemPromotions":[],"shopName":"","itemSize":null,"shippingMethodId":"14","categoryId":"7015","isNoPrice":false,"title":"","isLiked":false,"photos":[{"uri":"https://static.mercdn.net/item/detail/webp/photos/m13449050590_1.jpg?1781767214"}],"auction":null,"shop":null,"attributes":[]},{"id":"m23276307114","sellerId":"556062950","buyerId":"","status":"ITEM_STATUS_SOLD_OUT","name":"プラグマタ Switch2版","price":"6099","created":"1778121174","updated":"1778404807","thumbnails":["https://static.mercdn.net/thumb/item/webp/m23276307114_1.jpg?1778121174"],"itemType":"ITEM_TYPE_MERCARI","itemConditionId":"2","shippingPayerId":"2","itemSizes":[],"itemBrand":null,"itemPromotions":[],"shopName":"","itemSize":null,"shippingMethodId":"17","categoryId":"7015","isNoPrice":false,"title":"","isLiked":false,"photos":[{"uri":"https://static.mercdn.net/item/detail/webp/photos/m23276307114_1.jpg?1778121174"}],"auction":null,"shop":null,"attributes":[]},{"id":"m41283109020","sellerId":"738904411","buyerId":"","status":"ITEM_STATUS_TRADING","name":"プラグマタ PRAGMATA Switch2 ソフト","price":"5000","created":"1781448857","updated":"1781941686","thumbnails":["https://static.mercdn.net/thumb/item/webp/m41283109020_1.jpg?1781448857"],"itemType":"ITEM_TYPE_MERCARI","itemConditionId":"2","shippingPayerId":"2","itemSizes":[],"itemBrand":null,"itemPromotions":[],"shopName":"","itemSize":null,"shippingMethodId":"17","categoryId":"7015","isNoPrice":false,"title":"","isLiked":false,"photos":[{"uri":"https://static.mercdn.net/item/detail/webp/photos/m41283109020_1.jpg?1781448857"}],"auction":null,"shop":null,"attributes":[]},{"id":"m86432528209","sellerId":"496861329","buyerId":"","status":"ITEM_STATUS_TRADING","name":"プラグマタ Switch2 早期購入特典付き","price":"5680","created":"1781628619","updated":"1781689472","thumbnails":["https://static.mercdn.net/thumb/item/webp/m86432528209_1.jpg?1781628619"],"itemType":"ITEM_TYPE_MERCARI","itemConditionId":"3","shippingPayerId":"2","itemSizes":[],"itemBrand":null,"itemPromotions":[],"shopName":"","itemSize":null,"shippingMethodId":"14","categoryId":"7015","isNoPrice":false,"title":"","isLiked":false,"photos":[{"uri":"https://static.mercdn.net/item/detail/webp/photos/m86432528209_1.jpg?1781628619"}],"auction":null,"shop":null,"attributes":[]},{"id":"m72685238881","sellerId":"729072871","buyerId":"","status":"ITEM_STATUS_TRADING","name":"プラグマタ / PRAGMATA switch 2 ソフト キーカード版","price":"5600","created":"1781430966","updated":"1781818482","thumbnails":["https://static.mercdn.net/thumb/item/webp/m72685238881_1.jpg?1781430966"],"itemType":"ITEM_TYPE_MERCARI","itemConditionId":"3","shippingPayerId":"2","itemSizes":[],"itemBrand":null,"itemPromotions":[],"shopName":"","itemSize":null,"shippingMethodId":"14","categoryId":"7015","isNoPrice":false,"title":"","isLiked":false,"photos":[{"uri":"https://static.mercdn.net/item/detail/webp/photos/m72685238881_1.jpg?1781430966"}],"auction":null,"shop":null,"attributes":[]},{"id":"m19442037994","sellerId":"879341570","buyerId":"","status":"ITEM_STATUS_SOLD_OUT","name":"プラグマタ　Switch2","price":"6600","created":"1777809759","updated":"1778150854","thumbnails":["https://static.mercdn.net/thumb/item/webp/m19442037994_1.jpg?1777809759"],"itemType":"ITEM_TYPE_MERCARI","itemConditionId":"3","shippingPayerId":"2","itemSizes":[],"itemBrand":null,"itemPromotions":[],"shopName":"","itemSize":null,"shippingMethodId":"14","categoryId":"7015","isNoPrice":false,"title":"","isLiked":false,"photos":[{"uri":"https://static.mercdn.net/item/detail/webp/photos/m19442037994_1.jpg?1777809759"}],"auction":null,"shop":null,"attributes":[]},{"id":"m68847704409","sellerId":"669998648","buyerId":"","status":"ITEM_STATUS_TRADING","name":"新品未開封【Switch2】 プラグマタ [デラックスエディション]","price":"6400","created":"1781945063","updated":"1782093997","thumbnails":["https://static.mercdn.net/thumb/item/webp/m68847704409_1.jpg?1781945063"],"itemType":"ITEM_TYPE_MERCARI","itemConditionId":"1","shippingPayerId":"2","itemSizes":[],"itemBrand":null,"itemPromotions":[],"shopName":"","itemSize":null,"shippingMethodId":"17","categoryId":"7015","isNoPrice":false,"title":"","isLiked":false,"photos":[{"uri":"https://static.mercdn.net/item/detail/webp/photos/m68847704409_1.jpg?1781945063"}],"auction":null,"shop":null,"attributes":[]},{"id":"m76247245233","sellerId":"267091793","buyerId":"","status":"ITEM_STATUS_SOLD_OUT","name":"プチトマト様 リクエスト 2点 まとめ商品","price":"11800","created":"1781044904","updated":"1781205083","thumbnails":["https://static.mercdn.net/thumb/item/webp/m76247245233_1.jpg?1781044904"],"itemType":"ITEM_TYPE_MERCARI","itemConditionId":"2","shippingPayerId":"2","itemSizes":[],"itemBrand":null,"itemPromotions":[],"shopName":"","itemSize":null,"shippingMethodId":"14","categoryId":"1108","isNoPrice":false,"title":"","isLiked":false,"photos":[{"uri":"https://static.mercdn.net/item/detail/webp/photos/m76247245233_1.jpg?1781044904"}],"auction":null,"shop":null,"attributes":[]},{"id":"m33218558234","sellerId":"600562108","buyerId":"","status":"ITEM_STATUS_SOLD_OUT","name":"【新品】プラグマタ Switch2版 早期購入特典付き","price":"8500","created":"1777592672","updated":"1778143963","thumbnails":["https://static.mercdn.net/thumb/item/webp/m33218558234_1.jpg?1777592672"],"itemType":"ITEM_TYPE_MERCARI","itemConditionId":"1","shippingPayerId":"2","itemSizes":[],"itemBrand":null,"itemPromotions":[],"shopName":"","itemSize":null,"shippingMethodId":"17","categoryId":"7015","isNoPrice":false,"title":"","isLiked":false,"photos":[{"uri":"https://static.mercdn.net/item/detail/webp/photos/m33218558234_1.jpg?1777592672"}],"auction":null,"shop":null,"attributes":[]},{"id":"m88737247124","sellerId":"502929602","buyerId":"","status":"ITEM_STATUS_SOLD_OUT","name":"PRAGMATA Nintendo Switch ソフト　プラグマタ　特典付き","price":"5200","created":"1781414193","updated":"1781674159","thumbnails":["https://static.mercdn.net/thumb/item/webp/m88737247124_1.jpg?1781414193"],"itemType":"ITEM_TYPE_MERCARI","itemConditionId":"3","shippingPayerId":"2","itemSizes":[],"itemBrand":null,"itemPromotions":[],"shopName":"","itemSize":null,"shippingMethodId":"14","categoryId":"7015","isNoPrice":false,"title":"","isLiked":false,"photos":[{"uri":"https://static.mercdn.net/item/detail/webp/photos/m88737247124_1.jpg?1781414193"}],"auction":null,"shop":null,"attributes":[]},{"id":"m91404586784","sellerId":"764277930","buyerId":"","status":"ITEM_STATUS_SOLD_OUT","name":"Nintendo DREAM 2026年 6月号(付録付)","price":"980","created":"1779805570","updated":"1779981570","thumbnails":["https://static.mercdn.net/thumb/item/webp/m91404586784_1.jpg?1779805570"],"itemType":"ITEM_TYPE_MERCARI","itemConditionId":"3","shippingPayerId":"2","itemSizes":[],"itemBrand":null,"itemPromotions":[],"shopName":"","itemSize":null,"shippingMethodId":"17","categoryId":"10148","isNoPrice":false,"title":"","isLiked":false,"photos":[{"uri":"https://static.mercdn.net/item/detail/webp/photos/m91404586784_1.jpg?1779805570"}],"auction":null,"shop":null,"attributes":[]},{"id":"m45315987302","sellerId":"615379956","buyerId":"","status":"ITEM_STATUS_TRADING","name":"PRAGMATA プラグマタ　Nintendo Switch2 ソフト","price":"5800","created":"1781782290","updated":"1782011268","thumbnails":["https://static.mercdn.net/thumb/item/webp/m45315987302_1.jpg?1781782290"],"itemType":"ITEM_TYPE_MERCARI","itemConditionId":"2","shippingPayerId":"2","itemSizes":[],"itemBrand":null,"itemPromotions":[],"shopName":"","itemSize":null,"shippingMethodId":"17","categoryId":"7015","isNoPrice":false,"title":"","isLiked":false,"photos":[{"uri":"https://static.mercdn.net/item/detail/webp/photos/m45315987302_1.jpg?1781782290"}],"auction":null,"shop":null,"attributes":[]},{"id":"m14182278252","sellerId":"324744346","buyerId":"","status":"ITEM_STATUS_SOLD_OUT","name":"プラグマタ　 PRAGMATA Nintendo Switch","price":"6700","created":"1777711698","updated":"1777874154","thumbnails":["https://static.mercdn.net/thumb/item/webp/m14182278252_1.jpg?1777711698"],"itemType":"ITEM_TYPE_MERCARI","itemConditionId":"2","shippingPayerId":"2","itemSizes":[],"itemBrand":null,"itemPromotions":[],"shopName":"","itemSize":null,"shippingMethodId":"14","categoryId":"7015","isNoPrice":false,"title":"","isLiked":false,"photos":[{"uri":"https://static.mercdn.net/item/detail/webp/photos/m14182278252_1.jpg?1777711698"}],"auction":null,"shop":null,"attributes":[]},{"id":"m34900475235","sellerId":"761931782","buyerId":"","status":"ITEM_STATUS_TRADING","name":"プラグマタ switch2","price":"5500","created":"1781923224","updated":"1781999051","thumbnails":["https://static.mercdn.net/thumb/item/webp/m34900475235_1.jpg?1781923224"],"itemType":"ITEM_TYPE_MERCARI","itemConditionId":"3","shippingPayerId":"2","itemSizes":[],"itemBrand":null,"itemPromotions":[],"shopName":"","itemSize":null,"shippingMethodId":"17","categoryId":"7015","isNoPrice":false,"title":"","isLiked":false,"photos":[{"uri":"https://static.mercdn.net/item/detail/webp/photos/m34900475235_1.jpg?1781923224"}],"auction":null,"shop":null,"attributes":[]},{"id":"m20332712647","sellerId":"671519573","buyerId":"","status":"ITEM_STATUS_SOLD_OUT","name":"Switch2 プラグマタ　コード未使用","price":"7300","created":"1777615068","updated":"1777965060","thumbnails":["https://static.mercdn.net/thumb/item/webp/m20332712647_1.jpg?1777615068"],"itemType":"ITEM_TYPE_MERCARI","itemConditionId":"2","shippingPayerId":"2","itemSizes":[],"itemBrand":null,"itemPromotions":[],"shopName":"","itemSize":null,"shippingMethodId":"14","categoryId":"7015","isNoPrice":false,"title":"","isLiked":false,"photos":[{"uri":"https://static.mercdn.net/item/detail/webp/photos/m20332712647_1.jpg?1777615068"}],"auction":null,"shop":null,"attributes":[]},{"id":"m19918044363","sellerId":"635250162","buyerId":"","status":"ITEM_STATUS_SOLD_OUT","name":"プラグマタ Switch2版 早期特典あり","price":"6800","created":"1778245247","updated":"1778505396","thumbnails":["https://static.mercdn.net/thumb/item/webp/m19918044363_1.jpg?1778245247"],"itemType":"ITEM_TYPE_MERCARI","itemConditionId":"2","shippingPayerId":"2","itemSizes":[],"itemBrand":null,"itemPromotions":[],"shopName":"","itemSize":null,"shippingMethodId":"14","categoryId":"7015","isNoPrice":false,"title":"","isLiked":false,"photos":[{"uri":"https://static.mercdn.net/item/detail/webp/photos/m19918044363_1.jpg?1778245247"}],"auction":null,"shop":null,"attributes":[]},{"id":"m75786458038","sellerId":"102896589","buyerId":"","status":"ITEM_STATUS_SOLD_OUT","name":"【特典コード未使用】プラグマタ Nintendo Switch2","price":"6899","created":"1778124603","updated":"1778310155","thumbnails":["https://static.mercdn.net/thumb/item/webp/m75786458038_1.jpg?1778124603"],"itemType":"ITEM_TYPE_MERCARI","itemConditionId":"2","shippingPayerId":"2","itemSizes":[],"itemBrand":null,"itemPromotions":[],"shopName":"","itemSize":null,"shippingMethodId":"14","categoryId":"7015","isNoPrice":false,"title":"","isLiked":false,"photos":[{"uri":"https://static.mercdn.net/item/detail/webp/photos/m75786458038_1.jpg?1778124603"}],"auction":null,"shop":null,"attributes":[]},{"id":"m77946227744","sellerId":"478580910","buyerId":"","status":"ITEM_STATUS_TRADING","name":"Switch2 プラグマタ","price":"5500","created":"1781934347","updated":"1782077773","thumbnails":["https://static.mercdn.net/thumb/item/webp/m77946227744_1.jpg?1781934347"],"itemType":"ITEM_TYPE_MERCARI","itemConditionId":"3","shippingPayerId":"2","itemSizes":[],"itemBrand":null,"itemPromotions":[],"shopName":"","itemSize":null,"shippingMethodId":"14","categoryId":"7015","isNoPrice":false,"title":"","isLiked":false,"photos":[{"uri":"https://static.mercdn.net/item/detail/webp/photos/m77946227744_1.jpg?1781934347"}],"auction":null,"shop":null,"attributes":[]},{"id":"m18471152964","sellerId":"456275968","buyerId":"","status":"ITEM_STATUS_SOLD_OUT","name":"プラグマタ　Switch2","price":"6700","created":"1777535467","updated":"1778156613","thumbnails":["https://static.mercdn.net/thumb/item/webp/m18471152964_1.jpg?1777535467"],"itemType":"ITEM_TYPE_MERCARI","itemConditionId":"3","shippingPayerId":"2","itemSizes":[],"itemBrand":null,"itemPromotions":[],"shopName":"","itemSize":null,"shippingMethodId":"17","categoryId":"7015","isNoPrice":false,"title":"","isLiked":false,"photos":[{"uri":"https://static.mercdn.net/item/detail/webp/photos/m18471152964_1.jpg?1777535467"}],"auction":null,"shop":null,"attributes":[]},{"id":"m39526917439","sellerId":"740131411","buyerId":"","status":"ITEM_STATUS_SOLD_OUT","name":"プラグマタ switch","price":"7000","created":"1777816017","updated":"1778142927","thumbnails":["https://static.mercdn.net/thumb/item/webp/m39526917439_1.jpg?1777816017"],"itemType":"ITEM_TYPE_MERCARI","itemConditionId":"2","shippingPayerId":"2","itemSizes":[],"itemBrand":null,"itemPromotions":[],"shopName":"","itemSize":null,"shippingMethodId":"17","categoryId":"7015","isNoPrice":false,"title":"","isLiked":false,"photos":[{"uri":"https://static.mercdn.net/item/detail/webp/photos/m39526917439_1.jpg?1777816017"}],"auction":null,"shop":null,"attributes":[]},{"id":"m67983165851","sellerId":"544182459","buyerId":"","status":"ITEM_STATUS_SOLD_OUT","name":"【Switch2】プラグマタ　PRAGMATA コード付","price":"6900","created":"1777248343","updated":"1777458165","thumbnails":["https://static.mercdn.net/thumb/item/webp/m67983165851_1.jpg?1777248343"],"itemType":"ITEM_TYPE_MERCARI","itemConditionId":"2","shippingPayerId":"2","itemSizes":[],"itemBrand":null,"itemPromotions":[],"shopName":"","itemSize":null,"shippingMethodId":"17","categoryId":"7015","isNoPrice":false,"title":"","isLiked":false,"photos":[{"uri":"https://static.mercdn.net/item/detail/webp/photos/m67983165851_1.jpg?1777248343"}],"auction":null,"shop":null,"attributes":[]},{"id":"m40165898438","sellerId":"282221923","buyerId":"","status":"ITEM_STATUS_SOLD_OUT","name":"プラグマタ　Switch2ソフト","price":"6222","created":"1778578255","updated":"1778729914","thumbnails":["https://static.mercdn.net/thumb/item/webp/m40165898438_1.jpg?1778578255"],"itemType":"ITEM_TYPE_MERCARI","itemConditionId":"3","shippingPayerId":"2","itemSizes":[],"itemBrand":null,"itemPromotions":[],"shopName":"","itemSize":null,"shippingMethodId":"14","categoryId":"7015","isNoPrice":false,"title":"","isLiked":false,"photos":[{"uri":"https://static.mercdn.net/item/detail/webp/photos/m40165898438_1.jpg?1778578255"}],"auction":null,"shop":null,"attributes":[]},{"id":"m62321880547","sellerId":"795619979","buyerId":"","status":"ITEM_STATUS_SOLD_OUT","name":"Switch2 PRAGMATA プラグマタ","price":"6600","created":"1777792138","updated":"1778147387","thumbnails":["https://static.mercdn.net/thumb/item/webp/m62321880547_1.jpg?1777792138"],"itemType":"ITEM_TYPE_MERCARI","itemConditionId":"2","shippingPayerId":"2","itemSizes":[],"itemBrand":null,"itemPromotions":[],"shopName":"","itemSize":null,"shippingMethodId":"17","categoryId":"7015","isNoPrice":false,"title":"","isLiked":false,"photos":[{"uri":"https://static.mercdn.net/item/detail/webp/photos/m62321880547_1.jpg?1777792138"}],"auction":null,"shop":null,"attributes":[]},{"id":"m43028752758","sellerId":"595453928","buyerId":"","status":"ITEM_STATUS_SOLD_OUT","name":"プラグマタ　Switch","price":"7500","created":"1776943722","updated":"1777441069","thumbnails":["https://static.mercdn.net/thumb/item/webp/m43028752758_1.jpg?1776943722"],"itemType":"ITEM_TYPE_MERCARI","itemConditionId":"3","shippingPayerId":"2","itemSizes":[],"itemBrand":null,"itemPromotions":[],"shopName":"","itemSize":null,"shippingMethodId":"17","categoryId":"7015","isNoPrice":false,"title":"","isLiked":false,"photos":[{"uri":"https://static.mercdn.net/item/detail/webp/photos/m43028752758_1.jpg?1776943722"}],"auction":null,"shop":null,"attributes":[]},{"id":"m51168261528","sellerId":"430255169","buyerId":"","status":"ITEM_STATUS_SOLD_OUT","name":"プラグマタ PRAGMATA Switch2版","price":"6500","created":"1777991474","updated":"1778818879","thumbnails":["https://static.mercdn.net/thumb/item/webp/m51168261528_1.jpg?1777991474"],"itemType":"ITEM_TYPE_MERCARI","itemConditionId":"3","shippingPayerId":"2","itemSizes":[],"itemBrand":null,"itemPromotions":[],"shopName":"","itemSize":null,"shippingMethodId":"17","categoryId":"7015","isNoPrice":false,"title":"","isLiked":false,"photos":[{"uri":"https://static.mercdn.net/item/detail/webp/photos/m51168261528_1.jpg?1777991474"}],"auction":null,"shop":null,"attributes":[]},{"id":"m99260891309","sellerId":"269730809","buyerId":"","status":"ITEM_STATUS_SOLD_OUT","name":"プラグマタ　コード未使用","price":"6400","created":"1777871484","updated":"1778035823","thumbnails":["https://static.mercdn.net/thumb/item/webp/m99260891309_1.jpg?1777871484"],"itemType":"ITEM_TYPE_MERCARI","itemConditionId":"3","shippingPayerId":"2","itemSizes":[],"itemBrand":null,"itemPromotions":[],"shopName":"","itemSize":null,"shippingMethodId":"14","categoryId":"7015","isNoPrice":false,"title":"","isLiked":false,"photos":[{"uri":"https://static.mercdn.net/item/detail/webp/photos/m99260891309_1.jpg?1777871484"}],"auction":null,"shop":null,"attributes":[]},{"id":"m45368536927","sellerId":"498655399","buyerId":"","status":"ITEM_STATUS_SOLD_OUT","name":"【新品】プラグマタ ～ Switch 2","price":"7080","created":"1777025496","updated":"1777169961","thumbnails":["https://static.mercdn.net/thumb/item/webp/m45368536927_1.jpg?1777025496"],"itemType":"ITEM_TYPE_MERCARI","itemConditionId":"1","shippingPayerId":"2","itemSizes":[],"itemBrand":null,"itemPromotions":[],"shopName":"","itemSize":null,"shippingMethodId":"14","categoryId":"7015","isNoPrice":false,"title":"","isLiked":false,"photos":[{"uri":"https://static.mercdn.net/item/detail/webp/photos/m45368536927_1.jpg?1777025496"}],"auction":null,"shop":null,"attributes":[]},{"id":"m12939007175","sellerId":"279650101","buyerId":"","status":"ITEM_STATUS_SOLD_OUT","name":"プラグマタ-Nintendo Switch2【新品未開封シュリンク付】","price":"6400","created":"1781324855","updated":"1781530556","thumbnails":["https://static.mercdn.net/thumb/item/webp/m12939007175_1.jpg?1781324855"],"itemType":"ITEM_TYPE_MERCARI","itemConditionId":"1","shippingPayerId":"2","itemSizes":[],"itemBrand":null,"itemPromotions":[],"shopName":"","itemSize":null,"shippingMethodId":"17","categoryId":"7015","isNoPrice":false,"title":"","isLiked":false,"photos":[{"uri":"https://static.mercdn.net/item/detail/webp/photos/m12939007175_1.jpg?1781324855"}],"auction":null,"shop":null,"attributes":[]},{"id":"m43227961540","sellerId":"285712492","buyerId":"","status":"ITEM_STATUS_SOLD_OUT","name":"＜Switch2＞ プラグマタ デラックスエディション (未開封)","price":"8000","created":"1780503961","updated":"1780801055","thumbnails":["https://static.mercdn.net/thumb/item/webp/m43227961540_1.jpg?1780503961"],"itemType":"ITEM_TYPE_MERCARI","itemConditionId":"1","shippingPayerId":"2","itemSizes":[],"itemBrand":null,"itemPromotions":[],"shopName":"","itemSize":null,"shippingMethodId":"14","categoryId":"7015","isNoPrice":false,"title":"","isLiked":false,"photos":[{"uri":"https://static.mercdn.net/item/detail/webp/photos/m43227961540_1.jpg?1780503961"}],"auction":null,"shop":null,"attributes":[]},{"id":"m95439505006","sellerId":"285712492","buyerId":"","status":"ITEM_STATUS_SOLD_OUT","name":"通常版》Sw2 プラグマタ Nintendo Switch2 (未開封)","price":"7100","created":"1778773198","updated":"1779511706","thumbnails":["https://static.mercdn.net/thumb/item/webp/m95439505006_1.jpg?1778773198"],"itemType":"ITEM_TYPE_MERCARI","itemConditionId":"1","shippingPayerId":"2","itemSizes":[],"itemBrand":null,"itemPromotions":[],"shopName":"","itemSize":null,"shippingMethodId":"14","categoryId":"7015","isNoPrice":false,"title":"","isLiked":false,"photos":[{"uri":"https://static.mercdn.net/item/detail/webp/photos/m95439505006_1.jpg?1778773198"}],"auction":null,"shop":null,"attributes":[]},{"id":"m32533242667","sellerId":"986901611","buyerId":"","status":"ITEM_STATUS_SOLD_OUT","name":"プラグマタ switch2 購入特典付き【新品・未開封】","price":"7440","created":"1777280377","updated":"1777826302","thumbnails":["https://static.mercdn.net/thumb/item/webp/m32533242667_1.jpg?1777280377"],"itemType":"ITEM_TYPE_MERCARI","itemConditionId":"1","shippingPayerId":"2","itemSizes":[],"itemBrand":null,"itemPromotions":[],"shopName":"","itemSize":null,"shippingMethodId":"17","categoryId":"7015","isNoPrice":false,"title":"","isLiked":false,"photos":[{"uri":"https://static.mercdn.net/item/detail/webp/photos/m32533242667_1.jpg?1777280377"}],"auction":null,"shop":null,"attributes":[]},{"id":"m97740814538","sellerId":"285712492","buyerId":"","status":"ITEM_STATUS_SOLD_OUT","name":"通常版【未開封品】 プラグマタ PlayStation5","price":"7300","created":"1776694647","updated":"1776868261","thumbnails":["https://static.mercdn.net/thumb/item/webp/m97740814538_1.jpg?1776694647"],"itemType":"ITEM_TYPE_MERCARI","itemConditionId":"1","shippingPayerId":"2","itemSizes":[],"itemBrand":null,"itemPromotions":[],"shopName":"","itemSize":null,"shippingMethodId":"14","categoryId":"6985","isNoPrice":false,"title":"","isLiked":false,"photos":[{"uri":"https://static.mercdn.net/item/detail/webp/photos/m97740814538_1.jpg?1776694647"}],"auction":null,"shop":null,"attributes":[]},{"id":"2JSmfWwGdPsEt6Vs6S9j5G","sellerId":"0","buyerId":"","status":"ITEM_STATUS_SOLD_OUT","name":"【中古】ニンテンドースイッチ2ソフト プラグマタ デラックスエディション","price":"6300","created":"1781778408","updated":"1781879481","thumbnails":["https://assets.mercari-shops-static.com/-/small/plain/2JSmfWuxcNhqKS4Sxtkv8U.webp@webp"],"itemType":"ITEM_TYPE_BEYOND","itemConditionId":"3","shippingPayerId":"0","itemSizes":[],"itemBrand":null,"itemPromotions":[],"shopName":"","itemSize":null,"shippingMethodId":"0","categoryId":"702","isNoPrice":false,"title":"","isLiked":false,"photos":[{"uri":"https://assets.mercari-shops-static.com/-/large/plain/2JSmfWuxcNhqKS4Sxtkv8U.webp@webp"}],"auction":null,"shop":{"id":"YoUQXX6TT8X6C47LxjRZbH"},"attributes":[]},{"id":"2JR3X8gbrjKmTCB9dttR6h","sellerId":"0","buyerId":"","status":"ITEM_STATUS_SOLD_OUT","name":"【新品】ニンテンドースイッチ2ソフト プラグマタ [通常版]","price":"300","created":"1778469931","updated":"1781846644","thumbnails":["https://assets.mercari-shops-static.com/-/small/plain/2JR3X8e35ahhyc4b3zLp2X.webp@webp"],"itemType":"ITEM_TYPE_BEYOND","itemConditionId":"1","shippingPayerId":"0","itemSizes":[],"itemBrand":null,"itemPromotions":[],"shopName":"","itemSize":null,"shippingMethodId":"0","categoryId":"702","isNoPrice":false,"title":"","isLiked":false,"photos":[{"uri":"https://assets.mercari-shops-static.com/-/large/plain/2JR3X8e35ahhyc4b3zLp2X.webp@webp"}],"auction":null,"shop":{"id":"YoUQXX6TT8X6C47LxjRZbH"},"attributes":[]},{"id":"m64680805484","sellerId":"498655399","buyerId":"","status":"ITEM_STATUS_SOLD_OUT","name":"プラグマタ　Switch 2","price":"7080","created":"1777022314","updated":"1777166531","thumbnails":["https://static.mercdn.net/thumb/item/webp/m64680805484_1.jpg?1777022314"],"itemType":"ITEM_TYPE_MERCARI","itemConditionId":"1","shippingPayerId":"2","itemSizes":[],"itemBrand":null,"itemPromotions":[],"shopName":"","itemSize":null,"shippingMethodId":"14","categoryId":"7015","isNoPrice":false,"title":"","isLiked":false,"photos":[{"uri":"https://static.mercdn.net/item/detail/webp/photos/m64680805484_1.jpg?1777022314"}],"auction":null,"shop":null,"attributes":[]},{"id":"m57050544022","sellerId":"265123682","buyerId":"","status":"ITEM_STATUS_SOLD_OUT","name":"【DLC未使用】プラグマタ PRAGMATA Nintendo Switch2","price":"6000","created":"1781102462","updated":"1781350228","thumbnails":["https://static.mercdn.net/thumb/item/webp/m57050544022_1.jpg?1781102462"],"itemType":"ITEM_TYPE_MERCARI","itemConditionId":"2","shippingPayerId":"2","itemSizes":[],"itemBrand":null,"itemPromotions":[],"shopName":"","itemSize":null,"shippingMethodId":"14","categoryId":"7015","isNoPrice":false,"title":"","isLiked":false,"photos":[{"uri":"https://static.mercdn.net/item/detail/webp/photos/m57050544022_1.jpg?1781102462"}],"auction":null,"shop":null,"attributes":[]},{"id":"2JQHGxrd6UPBWbz9SKfS9p","sellerId":"0","buyerId":"","status":"ITEM_STATUS_SOLD_OUT","name":"【新品】 プラグマタ デラックスエディション Nintendo Switch 2 佐賀","price":"10800","created":"1777026762","updated":"1778392326","thumbnails":["https://assets.mercari-shops-static.com/-/small/plain/2JQHGxqjmkgGZ8UQPT2yiD.jpg@webp"],"itemType":"ITEM_TYPE_BEYOND","itemConditionId":"1","shippingPayerId":"0","itemSizes":[],"itemBrand":null,"itemPromotions":[],"shopName":"","itemSize":null,"shippingMethodId":"0","categoryId":"702","isNoPrice":false,"title":"","isLiked":false,"photos":[{"uri":"https://assets.mercari-shops-static.com/-/large/plain/2JQHGxqjmkgGZ8UQPT2yiD.jpg@webp"}],"auction":null,"shop":{"id":"d3kgLm8ps9DDXMeGkxkWz6"},"attributes":[]}],"components":[],"searchCondition":null,"searchConditionId":""}
